Workbook

Sheet Rent Insurance S - Consolidated
A1: Key | B1: Property | C1: Unit | D1: Resident | E1: Lease Start/Renewal Date | F1: Carrier | G1: Policy # | H1: Policy Start Date | I1: Expiration Date | J1: Status | K1: Reason | L1: Received | M1: Liability | N1: Last name | O1: Address
A2: =B2&"_"&C2 -> ATS_BG-300 | B2: ATS | C2: BG-300 | D2: Barnes, Viola Yvonne | E2: 45796 | F2: Assurant Liability | G2: RI 8495161 00 | H2: 45855 | I2: 46220 | J2: Active | L2: Yes | M2: 100000 | N2: Barnes | O2: =+INDEX('[1]Unit Setup View - Consolidated'!$AS:$AS,MATCH('Rent Insurance S - Consolidated'!$C2,'[1]Unit Setup View - Consolidated'!$AT:$AT,0)) -> 300 Brigade Court Ashland VA 23005
A3: =B3&"_"&C3 -> ATS_BG-302 | B3: ATS | C3: BG-302 | D3: Knightner, Monique Yvette | E3: 45786 | F3: Assurant Liability | G3: REN5506534 | H3: 45773 | I3: 46138 | J3: Active | L3: Yes | M3: 100000 | N3: Knightner | O3: =+INDEX('[1]Unit Setup View - Consolidated'!$AS:$AS,MATCH('Rent Insurance S - Consolidated'!$C3,'[1]Unit Setup View - Consolidated'!$AT:$AT,0)) -> 302 Brigade Court Ashland VA 23005
A4: =B4&"_"&C4 -> ATS_BG-304 | B4: ATS | C4: BG-304 | D4: Webber, Justin Michael | E4: 45737 | F4: eRenterPlan (LeasingDesk) | G4: 105050075 | H4: 45737 | I4: 46102 | J4: Active | L4: N/A | M4: 100000 | N4: Webber | O4: =+INDEX('[1]Unit Setup View - Consolidated'!$AS:$AS,MATCH('Rent Insurance S - Consolidated'!$C4,'[1]Unit Setup View - Consolidated'!$AT:$AT,0)) -> 304 Brigade Court Ashland VA 23005
A5: =B5&"_"&C5 -> ATS_BG-306 | B5: ATS | C5: BG-306 | D5: Sanderson, Donald Albert | E5: 45772 | F5: Geico | G5: REN 5501907 | H5: 45772 | I5: 46137 | J5: Active | L5: Yes | M5: 100000 | N5: Sanderson | O5: =+INDEX('[1]Unit Setup View - Consolidated'!$AS:$AS,MATCH('Rent Insurance S - Consolidated'!$C5,'[1]Unit Setup View - Consolidated'!$AT:$AT,0)) -> 306 Brigade Court Ashland VA 23005
A6: =B6&"_"&C6 -> ATS_BG-308 | B6: ATS | C6: BG-308 | D6: Mckinnon, Joshua | E6: 45797 | F6: Lemonade | G6: LP4ACAF8C88 | H6: 45914 | I6: 46279 | J6: Active | L6: Yes | M6: 100000 | N6: Mckinnon | O6: =+INDEX('[1]Unit Setup View - Consolidated'!$AS:$AS,MATCH('Rent Insurance S - Consolidated'!$C6,'[1]Unit Setup View - Consolidated'!$AT:$AT,0)) -> 308 Brigade Court Ashland VA 23005
A7: =B7&"_"&C7 -> ATS_BG-310 | B7: ATS | C7: BG-310 | D7: Capps, Lester | E7: 45775 | F7: Geico | G7: RIN 8427694 | H7: 45695 | I7: 46060 | J7: Active | L7: Yes | M7: 100000 | N7: Capps | O7: =+INDEX('[1]Unit Setup View - Consolidated'!$AS:$AS,MATCH('Rent Insurance S - Consolidated'!$C7,'[1]Unit Setup View - Consolidated'!$AT:$AT,0)) -> 310 Brigade Court Ashland VA 23005
A8: =B8&"_"&C8 -> ATS_BG-312 | B8: ATS | C8: BG-312 | D8: Rincon, Rhonny | E8: 45901 | F8: Progressive Insurance Company | G8: VAA281812 | H8: 45859 | I8: 46224 | J8: Active | L8: Yes | M8: 100000 | N8: Rincon | O8: =+INDEX('[1]Unit Setup View - Consolidated'!$AS:$AS,MATCH('Rent Insurance S - Consolidated'!$C8,'[1]Unit Setup View - Consolidated'!$AT:$AT,0)) -> 312 Brigade Court Ashland VA 23005
A9: =B9&"_"&C9 -> ATS_BG-314 | B9: ATS | C9: BG-314 | D9: Jones, Allen | E9: 45717 | F9: eRenterPlan (LeasingDesk) | G9: 102536980 | H9: 44590 | I9: 46051 | J9: Active | L9: N/A | M9: 100000 | N9: Jones | O9: =+INDEX('[1]Unit Setup View - Consolidated'!$AS:$AS,MATCH('Rent Insurance S - Consolidated'!$C9,'[1]Unit Setup View - Consolidated'!$AT:$AT,0)) -> 314 Brigade Court Ashland VA 23005
A10: =B10&"_"&C10 -> ATS_BG-316 | B10: ATS | C10: BG-316 | D10: klassen, aaron Frank | E10: 45966 | F10: eRenterPlan (LeasingDesk) | G10: 105567256 | H10: 45965 | I10: 46330 | J10: Active | L10: N/A | M10: 100000 | N10: klassen | O10: =+INDEX('[1]Unit Setup View - Consolidated'!$AS:$AS,MATCH('Rent Insurance S - Consolidated'!$C10,'[1]Unit Setup View - Consolidated'!$AT:$AT,0)) -> 316 Brigade Court Ashland VA 23005
A11: =B11&"_"&C11 -> ATS_BG-318 | B11: ATS | C11: BG-318 | D11: Holmes, Nicole | E11: 45627 | F11: Travelers Insurance Company | G11: 6160330026341 | H11: 45476 | I11: 45841 | J11: Cancelled | L11: Yes | M11: 100000 | N11: Holmes | O11: =+INDEX('[1]Unit Setup View - Consolidated'!$AS:$AS,MATCH('Rent Insurance S - Consolidated'!$C11,'[1]Unit Setup View - Consolidated'!$AT:$AT,0)) -> 318 Brigade Court Ashland VA 23005
A12: =B12&"_"&C12 -> ATS_BG-320 | B12: ATS | C12: BG-320 | D12: Salazar, Emelin Yuliana | E12: 45782 | F12: Trisura Ins Company | G12: 89720665 | H12: 45782 | I12: 46147 | J12: Active | L12: Yes | M12: 100000 | N12: Salazar | O12: =+INDEX('[1]Unit Setup View - Consolidated'!$AS:$AS,MATCH('Rent Insurance S - Consolidated'!$C12,'[1]Unit Setup View - Consolidated'!$AT:$AT,0)) -> 320 Brigade Court Ashland VA 23005
A13: =B13&"_"&C13 -> ATS_BG-322 | B13: ATS | C13: BG-322 | D13: Levy, Christopher Ryan | E13: 45810 | F13: Trisura Ins Company | G13: 89942370 | H13: 45806 | I13: 46171 | J13: Active | L13: Yes | M13: 100000 | N13: Levy | O13: =+INDEX('[1]Unit Setup View - Consolidated'!$AS:$AS,MATCH('Rent Insurance S - Consolidated'!$C13,'[1]Unit Setup View - Consolidated'!$AT:$AT,0)) -> 322 Brigade Court Ashland VA 23005
A14: =B14&"_"&C14 -> ATS_BG-324 | B14: ATS | C14: BG-324 | D14: Estrada Garcia, Joe Angel Francisco | E14: 45793 | F14: eRenterPlan (LeasingDesk) | G14: 105172266 | H14: 45793 | I14: 46158 | J14: active | L14: N/A | M14: 100000 | N14: Estrada Garcia | O14: =+INDEX('[1]Unit Setup View - Consolidated'!$AS:$AS,MATCH('Rent Insurance S - Consolidated'!$C14,'[1]Unit Setup View - Consolidated'!$AT:$AT,0)) -> 324 Brigade Court Ashland VA 23005
A15: =B15&"_"&C15 -> ATS_BG-326 | B15: ATS | C15: BG-326 | D15: Gray, Douglas Allen | E15: 45860 | F15: eRenterPlan (LeasingDesk) | G15: 105331498 | H15: 45856 | I15: 46221 | J15: Active | L15: N/A | M15: 100000 | N15: Gray | O15: =+INDEX('[1]Unit Setup View - Consolidated'!$AS:$AS,MATCH('Rent Insurance S - Consolidated'!$C15,'[1]Unit Setup View - Consolidated'!$AT:$AT,0)) -> 326 Brigade Court Ashland VA 23005
A16: =B16&"_"&C16 -> ATS_BG-328 | B16: ATS | C16: BG-328 | J16: Vacant | L16: No | O16: =+INDEX('[1]Unit Setup View - Consolidated'!$AS:$AS,MATCH('Rent Insurance S - Consolidated'!$C16,'[1]Unit Setup View - Consolidated'!$AT:$AT,0)) -> 328 Brigade Court Ashland VA 23005
A17: =B17&"_"&C17 -> ATS_BP-100 | B17: ATS | C17: BP-100 | D17: Ferguson, Brian | E17: 45841 | F17: Safeco | G17: OF2996089 | H17: 45700 | I17: 46065 | J17: Active | L17: Yes | M17: 100000 | N17: Ferguson | O17: =+INDEX('[1]Unit Setup View - Consolidated'!$AS:$AS,MATCH('Rent Insurance S - Consolidated'!$C17,'[1]Unit Setup View - Consolidated'!$AT:$AT,0)) -> 100 Bruton Parrish Ashland VA 23005
A18: =B18&"_"&C18 -> ATS_BP-101 | B18: ATS | C18: BP-101 | J18: Vacant | L18: No | O18: =+INDEX('[1]Unit Setup View - Consolidated'!$AS:$AS,MATCH('Rent Insurance S - Consolidated'!$C18,'[1]Unit Setup View - Consolidated'!$AT:$AT,0)) -> 101 Bruton Parrish Ashland VA 23005
A19: =B19&"_"&C19 -> ATS_BP-102 | B19: ATS | C19: BP-102 | D19: Quick, Leon | E19: 45930 | F19: Nationwide | G19: 5345HS000961 | H19: 45922 | I19: 46287 | J19: Active | L19: Yes | M19: 100000 | N19: Quick | O19: =+INDEX('[1]Unit Setup View - Consolidated'!$AS:$AS,MATCH('Rent Insurance S - Consolidated'!$C19,'[1]Unit Setup View - Consolidated'!$AT:$AT,0)) -> 102 Bruton Parrish Ashland VA 23005
A20: =B20&"_"&C20 -> ATS_BP-103 | B20: ATS | C20: BP-103 | D20: Grim, Jonathan | E20: 45857 | F20: Homebody | G20: RTH11467668 | H20: 44390 | I20: 46219 | J20: Active | L20: Yes | M20: 100000 | N20: Grim | O20: =+INDEX('[1]Unit Setup View - Consolidated'!$AS:$AS,MATCH('Rent Insurance S - Consolidated'!$C20,'[1]Unit Setup View - Consolidated'!$AT:$AT,0)) -> 103 Bruton Parrish Ashland VA 23005
A21: =B21&"_"&C21 -> ATS_BP-104 | B21: ATS | C21: BP-104 | D21: Mccrea, Katherine | E21: 45962 | F21: Liberty Mutual | G21: H4J2312611167541 | H21: 45598 | I21: 45963 | J21: Cancelled | L21: Yes | M21: 100000 | N21: Mccrea | O21: =+INDEX('[1]Unit Setup View - Consolidated'!$AS:$AS,MATCH('Rent Insurance S - Consolidated'!$C21,'[1]Unit Setup View - Consolidated'!$AT:$AT,0)) -> 104 Bruton Parrish Ashland VA 23005
A22: =B22&"_"&C22 -> ATS_BP-105 | B22: ATS | C22: BP-105 | D22: Ward, Jacob Thomas | E22: 45737 | F22: TheGuarantors | G22: 89247741 | H22: 45737 | I22: 46102 | J22: Active | L22: Yes | M22: 100000 | N22: Ward | O22: =+INDEX('[1]Unit Setup View - Consolidated'!$AS:$AS,MATCH('Rent Insurance S - Consolidated'!$C22,'[1]Unit Setup View - Consolidated'!$AT:$AT,0)) -> 105 Bruton Parrish Ashland VA 23005
A23: =B23&"_"&C23 -> ATS_BP-106 | B23: ATS | C23: BP-106 | D23: Hubbard, Marcus | E23: 45658 | F23: eRenterPlan (LeasingDesk) | G23: 102524697 | H23: 44586 | I23: 46047 | J23: Active | L23: N/A | M23: 100000 | N23: Hubbard | O23: =+INDEX('[1]Unit Setup View - Consolidated'!$AS:$AS,MATCH('Rent Insurance S - Consolidated'!$C23,'[1]Unit Setup View - Consolidated'!$AT:$AT,0)) -> 106 Bruton Parrish Ashland VA 23005
A24: =B24&"_"&C24 -> ATS_BP-107 | B24: ATS | C24: BP-107 | D24: Marrin, Colin Patrick | E24: 45723 | F24: USAA Insurance Company | G24: CIC-029402293 REN001 | H24: 45721 | I24: 46087 | J24: Active | L24: Yes | M24: 100000 | N24: Marrin | O24: =+INDEX('[1]Unit Setup View - Consolidated'!$AS:$AS,MATCH('Rent Insurance S - Consolidated'!$C24,'[1]Unit Setup View - Consolidated'!$AT:$AT,0)) -> 107 Bruton Parrish Ashland VA 23005
A25: =B25&"_"&C25 -> ATS_BP-108 | B25: ATS | C25: BP-108 | J25: Vacant | L25: No | O25: =+INDEX('[1]Unit Setup View - Consolidated'!$AS:$AS,MATCH('Rent Insurance S - Consolidated'!$C25,'[1]Unit Setup View - Consolidated'!$AT:$AT,0)) -> 108 Bruton Parrish Ashland VA 23005
A26: =B26&"_"&C26 -> ATS_BP-109 | B26: ATS | C26: BP-109 | J26: Vacant | L26: No | O26: =+INDEX('[1]Unit Setup View - Consolidated'!$AS:$AS,MATCH('Rent Insurance S - Consolidated'!$C26,'[1]Unit Setup View - Consolidated'!$AT:$AT,0)) -> 109 Bruton Parrish Ashland VA 23005
A27: =B27&"_"&C27 -> ATS_BP-110 | B27: ATS | C27: BP-110 | D27: Hinton, Jamie J | E27: 45639 | F27: eRenterPlan (LeasingDesk) | G27: 104854847 | H27: 45637 | I27: 46002 | J27: Active | L27: N/A | M27: 100000 | N27: Hinton | O27: =+INDEX('[1]Unit Setup View - Consolidated'!$AS:$AS,MATCH('Rent Insurance S - Consolidated'!$C27,'[1]Unit Setup View - Consolidated'!$AT:$AT,0)) -> 110 Bruton Parrish Ashland VA 23005
A28: =B28&"_"&C28 -> ATS_BP-111 | B28: ATS | C28: BP-111 | D28: Gibson, Richard | E28: 45901 | F28: State Farm Insurance | G28: 46C7N7869 | H28: 45527 | I28: 45892 | J28: Cancelled | L28: Yes | M28: 100000 | N28: Gibson | O28: =+INDEX('[1]Unit Setup View - Consolidated'!$AS:$AS,MATCH('Rent Insurance S - Consolidated'!$C28,'[1]Unit Setup View - Consolidated'!$AT:$AT,0)) -> 111 Bruton Parrish Ashland VA 23005
A29: =B29&"_"&C29 -> ATS_BP-112 | B29: ATS | C29: BP-112 | D29: Henry, Dayjuan Elian | E29: 45932 | F29: eRenterPlan (LeasingDesk) | G29: 105504685 | H29: 45932 | I29: 45966 | J29: Cancelled | K29: Due to Non-payment | L29: N/A | M29: 100000 | N29: Henry | O29: =+INDEX('[1]Unit Setup View - Consolidated'!$AS:$AS,MATCH('Rent Insurance S - Consolidated'!$C29,'[1]Unit Setup View - Consolidated'!$AT:$AT,0)) -> 112 Bruton Parrish Ashland VA 23005
A30: =B30&"_"&C30 -> ATS_BP-113 | B30: ATS | C30: BP-113 | D30: sousa, Cleiton | E30: 45804 | J30: Override | K30: By TFITZGERALD1 - 04/18/2023 : Will Provide asap. | L30: No | N30: sousa | O30: =+INDEX('[1]Unit Setup View - Consolidated'!$AS:$AS,MATCH('Rent Insurance S - Consolidated'!$C30,'[1]Unit Setup View - Consolidated'!$AT:$AT,0)) -> 113 Bruton Parrish Ashland VA 23005
A31: =B31&"_"&C31 -> ATS_BP-114 | B31: ATS | C31: BP-114 | D31: Davis, Debora Santia | E31: 45595 | F31: eRenterPlan (LeasingDesk) | G31: 104761896 | H31: 45595 | I31: 45962 | J31: Cancelled | K31: Due to Non-payment | L31: N/A | M31: 100000 | N31: Davis | O31: =+INDEX('[1]Unit Setup View - Consolidated'!$AS:$AS,MATCH('Rent Insurance S - Consolidated'!$C31,'[1]Unit Setup View - Consolidated'!$AT:$AT,0)) -> 114 Bruton Parrish Ashland VA 23005
A32: =B32&"_"&C32 -> ATS_BP-115 | B32: ATS | C32: BP-115 | D32: Jaffe, Angela Rebecca | E32: 45673 | F32: Central Mutual Ins. Company | G32: FMH3433628 | H32: 45813 | I32: 46178 | J32: Active | L32: Yes | M32: 100000 | N32: Jaffe | O32: =+INDEX('[1]Unit Setup View - Consolidated'!$AS:$AS,MATCH('Rent Insurance S - Consolidated'!$C32,'[1]Unit Setup View - Consolidated'!$AT:$AT,0)) -> 115 Bruton Parrish Ashland VA 23005
A33: =B33&"_"&C33 -> ATS_BP-116 | B33: ATS | C33: BP-116 | D33: Joseph, Paula Nezra | E33: 45839 | F33: Allstate Insurance | G33: 818823857 | H33: 45839 | I33: 46204 | J33: Active | L33: Yes | M33: 100000 | N33: Joseph | O33: =+INDEX('[1]Unit Setup View - Consolidated'!$AS:$AS,MATCH('Rent Insurance S - Consolidated'!$C33,'[1]Unit Setup View - Consolidated'!$AT:$AT,0)) -> 116 Bruton Parrish Ashland VA 23005
A34: =B34&"_"&C34 -> ATS_BP-117 | B34: ATS | C34: BP-117 | D34: Jones, Richard | E34: 45944 | F34: Geico | G34: REN5970572 | H34: 45944 | I34: 46309 | J34: Active | L34: Yes | M34: 100000 | N34: Jones | O34: =+INDEX('[1]Unit Setup View - Consolidated'!$AS:$AS,MATCH('Rent Insurance S - Consolidated'!$C34,'[1]Unit Setup View - Consolidated'!$AT:$AT,0)) -> 117 Bruton Parrish Ashland VA 23005
A35: =B35&"_"&C35 -> ATS_BP-118 | B35: ATS | C35: BP-118 | D35: Argueta, Aryani Mixue | E35: 45944 | J35: Override | K35: By TFITZGERALD1 - 09/26/2023 : Sending new policy | L35: No | N35: Argueta | O35: =+INDEX('[1]Unit Setup View - Consolidated'!$AS:$AS,MATCH('Rent Insurance S - Consolidated'!$C35,'[1]Unit Setup View - Consolidated'!$AT:$AT,0)) -> 118 Bruton Parrish Ashland VA 23005
A36: =B36&"_"&C36 -> ATS_BP-119 | B36: ATS | C36: BP-119 | J36: Vacant | L36: No | O36: =+INDEX('[1]Unit Setup View - Consolidated'!$AS:$AS,MATCH('Rent Insurance S - Consolidated'!$C36,'[1]Unit Setup View - Consolidated'!$AT:$AT,0)) -> 119 Bruton Parrish Ashland VA 23005
A37: =B37&"_"&C37 -> ATS_BP-121 | B37: ATS | C37: BP-121 | D37: Ezer, Mehmet | E37: 45839 | F37: Geico | G37: 4674009 | H37: 45837 | I37: 46202 | J37: Active | L37: Yes | M37: 100000 | N37: Ezer | O37: =+INDEX('[1]Unit Setup View - Consolidated'!$AS:$AS,MATCH('Rent Insurance S - Consolidated'!$C37,'[1]Unit Setup View - Consolidated'!$AT:$AT,0)) -> 121 Bruton Parrish Ashland VA 23005
A38: =B38&"_"&C38 -> ATS_BP-123 | B38: ATS | C38: BP-123 | D38: Pendleton, Alex Maurice | E38: 45703 | F38: eRenterPlan (LeasingDesk) | G38: 103397586 | H38: 45030 | I38: 46126 | J38: Active | L38: N/A | M38: 100000 | N38: Pendleton | O38: =+INDEX('[1]Unit Setup View - Consolidated'!$AS:$AS,MATCH('Rent Insurance S - Consolidated'!$C38,'[1]Unit Setup View - Consolidated'!$AT:$AT,0)) -> 123 Bruton Parrish Ashland VA 23005
A39: =B39&"_"&C39 -> ATS_CW-400 | B39: ATS | C39: CW-400 | D39: Eskridge, Sarah | E39: 45757 | F39: State Farm Insurance | G39: 46-GE-S186-3 | H39: 45757 | I39: 46122 | J39: Active | L39: Yes | M39: 300000 | N39: Eskridge | O39: =+INDEX('[1]Unit Setup View - Consolidated'!$AS:$AS,MATCH('Rent Insurance S - Consolidated'!$C39,'[1]Unit Setup View - Consolidated'!$AT:$AT,0)) -> 400 Cornwallis Court Ashland VA 23005
A40: =B40&"_"&C40 -> ATS_CW-401 | B40: ATS | C40: CW-401 | D40: Wallace, Raven | E40: 45805 | F40: Liberty Mutual | G40: H4J23195384145 | H40: 45805 | I40: 46170 | J40: Active | L40: Yes | M40: 100000 | N40: Wallace | O40: =+INDEX('[1]Unit Setup View - Consolidated'!$AS:$AS,MATCH('Rent Insurance S - Consolidated'!$C40,'[1]Unit Setup View - Consolidated'!$AT:$AT,0)) -> 401 Cornwallis Court Ashland VA 23005
A41: =B41&"_"&C41 -> ATS_CW-402 | B41: ATS | C41: CW-402 | D41: Pyers, Kris Nichole | E41: 45634 | F41: Assurant Liability | G41: RIO112790 | H41: 45634 | I41: 45999 | J41: Pending Cancellation | L41: Yes | M41: 100000 | N41: Pyers | O41: =+INDEX('[1]Unit Setup View - Consolidated'!$AS:$AS,MATCH('Rent Insurance S - Consolidated'!$C41,'[1]Unit Setup View - Consolidated'!$AT:$AT,0)) -> 402 Cornwallis Court Ashland VA 23005
A42: =B42&"_"&C42 -> ATS_CW-403 | B42: ATS | C42: CW-403 | D42: Hall, Kyanne | E42: 45901 | F42: USAA Insurance Company | G42: 5851538 | H42: 45900 | I42: 46265 | J42: Active | L42: Yes | M42: 100000 | N42: Hall | O42: =+INDEX('[1]Unit Setup View - Consolidated'!$AS:$AS,MATCH('Rent Insurance S - Consolidated'!$C42,'[1]Unit Setup View - Consolidated'!$AT:$AT,0)) -> 403 Cornwallis Court Ashland VA 23005
A43: =B43&"_"&C43 -> ATS_CW-404 | B43: ATS | C43: CW-404 | D43: Hall, Patrick | E43: 45638 | F43: State Farm Insurance | G43: 46-E2-P704-9 | H43: 45617 | I43: 45982 | J43: Pending Cancellation | L43: Yes | M43: 100000 | N43: Hall | O43: =+INDEX('[1]Unit Setup View - Consolidated'!$AS:$AS,MATCH('Rent Insurance S - Consolidated'!$C43,'[1]Unit Setup View - Consolidated'!$AT:$AT,0)) -> 404 Cornwallis Court Ashland VA 23005
A44: =B44&"_"&C44 -> ATS_CW-405 | B44: ATS | C44: CW-405 | D44: Richardson, Horace | E44: 45791 | F44: USAA Insurance Company | G44: GAR 028467436 REN 002 | H44: 45587 | I44: 45952 | J44: Cancelled | L44: Yes | M44: 100000 | N44: Richardson | O44: =+INDEX('[1]Unit Setup View - Consolidated'!$AS:$AS,MATCH('Rent Insurance S - Consolidated'!$C44,'[1]Unit Setup View - Consolidated'!$AT:$AT,0)) -> 405 Cornwallis Court Ashland VA 23005
A45: =B45&"_"&C45 -> ATS_CW-406 | B45: ATS | C45: CW-406 | D45: LaMontagne, Michelle Sarah | E45: 45810 | J45: Override | K45: By BTRIVETT - 06/02/2025 : teresa never filed. Uploading now. | L45: No | N45: LaMontagne | O45: =+INDEX('[1]Unit Setup View - Consolidated'!$AS:$AS,MATCH('Rent Insurance S - Consolidated'!$C45,'[1]Unit Setup View - Consolidated'!$AT:$AT,0)) -> 406 Cornwallis Court Ashland VA 23005
A46: =B46&"_"&C46 -> ATS_CW-407 | B46: ATS | C46: CW-407 | D46: Collins, Nichole | E46: 45717 | F46: USAA Insurance Company | G46: CIC 023484477 REN001 | H46: 45616 | I46: 45981 | J46: Pending Cancellation | L46: Yes | M46: 100000 | N46: Collins | O46: =+INDEX('[1]Unit Setup View - Consolidated'!$AS:$AS,MATCH('Rent Insurance S - Consolidated'!$C46,'[1]Unit Setup View - Consolidated'!$AT:$AT,0)) -> 407 Cornwallis Court Ashland VA 23005
A47: =B47&"_"&C47 -> ATS_CW-408 | B47: ATS | C47: CW-408 | D47: Arthur, Stephen | E47: 45930 | F47: Erie Insurance Group | G47: Q582908990 | H47: 45594 | I47: 45959 | J47: Cancelled | L47: Yes | M47: 100000 | N47: Arthur | O47: =+INDEX('[1]Unit Setup View - Consolidated'!$AS:$AS,MATCH('Rent Insurance S - Consolidated'!$C47,'[1]Unit Setup View - Consolidated'!$AT:$AT,0)) -> 408 Cornwallis Court Ashland VA 23005
A48: =B48&"_"&C48 -> ATS_CW-409 | B48: ATS | C48: CW-409 | D48: Avilan, Cesar Augusto | E48: 45751 | F48: AAA | G48: VAH4232095448 | H48: 45725 | I48: 46090 | J48: Active | L48: Yes | M48: 100000 | N48: Avilan | O48: =+INDEX('[1]Unit Setup View - Consolidated'!$AS:$AS,MATCH('Rent Insurance S - Consolidated'!$C48,'[1]Unit Setup View - Consolidated'!$AT:$AT,0)) -> 409 Cornwallis Court Ashland VA 23005
A49: =B49&"_"&C49 -> ATS_CW-410 | B49: ATS | C49: CW-410 | D49: Hawthorne, Curtis | E49: 45930 | F49: Liberty Mutual | G49: H4J23152499175 | H49: 45922 | I49: 46287 | J49: Active | L49: Yes | M49: 100000 | N49: Hawthorne | O49: =+INDEX('[1]Unit Setup View - Consolidated'!$AS:$AS,MATCH('Rent Insurance S - Consolidated'!$C49,'[1]Unit Setup View - Consolidated'!$AT:$AT,0)) -> 410 Cornwallis Court Ashland VA 23005
A50: =B50&"_"&C50 -> ATS_CW-411 | B50: ATS | C50: CW-411 | D50: Wright, Keona Sheneice | E50: 45973 | F50: eRenterPlan (LeasingDesk) | G50: 105580484 | H50: 45973 | I50: 46338 | J50: Active | L50: N/A | M50: 100000 | N50: Wright | O50: =+INDEX('[1]Unit Setup View - Consolidated'!$AS:$AS,MATCH('Rent Insurance S - Consolidated'!$C50,'[1]Unit Setup View - Consolidated'!$AT:$AT,0)) -> 411 Cornwallis Court Ashland VA 23005
A51: =B51&"_"&C51 -> ATS_CW-412 | B51: ATS | C51: CW-412 | D51: Robinson, Michelle PAINTER | E51: 45958 | F51: eRenterPlan (LeasingDesk) | G51: 105549989 | H51: 45957 | I51: 45990 | J51: Pending Cancellation | K51: Due to Non-payment | L51: N/A | M51: 100000 | N51: Robinson | O51: =+INDEX('[1]Unit Setup View - Consolidated'!$AS:$AS,MATCH('Rent Insurance S - Consolidated'!$C51,'[1]Unit Setup View - Consolidated'!$AT:$AT,0)) -> 412 Cornwallis Court Ashland VA 23005
A52: =B52&"_"&C52 -> ATS_CW-413 | B52: ATS | C52: CW-413 | D52: Straus, Jarrod | E52: 45933 | F52: Homebody | G52: RTH12787444 | H52: 45933 | I52: 46298 | J52: Active | L52: Yes | M52: 100000 | N52: Straus | O52: =+INDEX('[1]Unit Setup View - Consolidated'!$AS:$AS,MATCH('Rent Insurance S - Consolidated'!$C52,'[1]Unit Setup View - Consolidated'!$AT:$AT,0)) -> 413 Cornwallis Court Ashland VA 23005
A53: =B53&"_"&C53 -> ATS_CW-414 | B53: ATS | C53: CW-414 | D53: Hargrove, Sylvester | E53: 45778 | F53: State Farm Insurance | G53: 46-BY-K495-9 | H53: 45380 | I53: 45745 | J53: Cancelled | L53: Yes | M53: 300000 | N53: Hargrove | O53: =+INDEX('[1]Unit Setup View - Consolidated'!$AS:$AS,MATCH('Rent Insurance S - Consolidated'!$C53,'[1]Unit Setup View - Consolidated'!$AT:$AT,0)) -> 414 Cornwallis Court Ashland VA 23005
A54: =B54&"_"&C54 -> ATS_CW-416 | B54: ATS | C54: CW-416 | D54: Smithers, Marita D | E54: 45881 | F54: eRenterPlan (LeasingDesk) | G54: 105391876 | H54: 45880 | I54: 46245 | J54: Active | L54: N/A | M54: 100000 | N54: Smithers | O54: =+INDEX('[1]Unit Setup View - Consolidated'!$AS:$AS,MATCH('Rent Insurance S - Consolidated'!$C54,'[1]Unit Setup View - Consolidated'!$AT:$AT,0)) -> 416 Cornwallis Court Ashland VA 23005
A55: =B55&"_"&C55 -> ATS_CW-418 | B55: ATS | C55: CW-418 | D55: Moss, Tara G | E55: 45797 | F55: Trisura Ins Company | G55: 89381363 | H55: 45797 | I55: 46162 | J55: Active | L55: Yes | M55: 100000 | N55: Moss | O55: =+INDEX('[1]Unit Setup View - Consolidated'!$AS:$AS,MATCH('Rent Insurance S - Consolidated'!$C55,'[1]Unit Setup View - Consolidated'!$AT:$AT,0)) -> 418 Cornwallis Court Ashland VA 23005
A56: =B56&"_"&C56 -> ATS_CW-420 | B56: ATS | C56: CW-420 | D56: Long, Nicole Michelle | E56: 45755 | F56: eRenterPlan (LeasingDesk) | G56: 102615323 | H56: 44653 | I56: 46114 | J56: Active | L56: N/A | M56: 100000 | N56: Long | O56: =+INDEX('[1]Unit Setup View - Consolidated'!$AS:$AS,MATCH('Rent Insurance S - Consolidated'!$C56,'[1]Unit Setup View - Consolidated'!$AT:$AT,0)) -> 420 Cornwallis Court Ashland VA 23005
A57: =B57&"_"&C57 -> ATS_CW-422 | B57: ATS | C57: CW-422 | D57: Pena, Oscar | E57: 45655 | F57: Liberty Mutual | G57: H4J-231-805533-75 5 0 | H57: 45883 | I57: 46248 | J57: Active | L57: Yes | M57: 100000 | N57: Pena | O57: =+INDEX('[1]Unit Setup View - Consolidated'!$AS:$AS,MATCH('Rent Insurance S - Consolidated'!$C57,'[1]Unit Setup View - Consolidated'!$AT:$AT,0)) -> 422 Cornwallis Court Ashland VA 23005
A58: =B58&"_"&C58 -> ATS_CW-424 | B58: ATS | C58: CW-424 | D58: Stokes, Bethany | E58: 45879 | F58: ESURANCE | G58: PAVA7266404 | H58: 45865 | I58: 46049 | J58: Active | L58: Yes | M58: 100000 | N58: Stokes | O58: =+INDEX('[1]Unit Setup View - Consolidated'!$AS:$AS,MATCH('Rent Insurance S - Consolidated'!$C58,'[1]Unit Setup View - Consolidated'!$AT:$AT,0)) -> 424 Cornwallis Court Ashland VA 23005
A59: =B59&"_"&C59 -> ATS_CW-426 | B59: ATS | C59: CW-426 | J59: Vacant | L59: No | O59: =+INDEX('[1]Unit Setup View - Consolidated'!$AS:$AS,MATCH('Rent Insurance S - Consolidated'!$C59,'[1]Unit Setup View - Consolidated'!$AT:$AT,0)) -> 426 Cornwallis Court Ashland VA 23005
A60: =B60&"_"&C60 -> ATS_CW-428 | B60: ATS | C60: CW-428 | D60: Willson, Jonell Karen | E60: 45734 | F60: Trisura Insurance Company | G60: 89258662 | H60: 45734 | I60: 46099 | J60: Active | L60: Yes | M60: 100000 | N60: Willson | O60: =+INDEX('[1]Unit Setup View - Consolidated'!$AS:$AS,MATCH('Rent Insurance S - Consolidated'!$C60,'[1]Unit Setup View - Consolidated'!$AT:$AT,0)) -> 428 Cornwallis Court Ashland VA 23005
A61: =B61&"_"&C61 -> ATS_CW-430 | B61: ATS | C61: CW-430 | D61: Jones, DeAndre James | E61: 45444 | F61: TheGuarantors | G61: 86425408 | H61: 45457 | I61: 45822 | J61: Cancelled | L61: Yes | M61: 100000 | N61: Jones | O61: =+INDEX('[1]Unit Setup View - Consolidated'!$AS:$AS,MATCH('Rent Insurance S - Consolidated'!$C61,'[1]Unit Setup View - Consolidated'!$AT:$AT,0)) -> 430 Cornwallis Court Ashland VA 23005
A62: =B62&"_"&C62 -> ATS_CW-432 | B62: ATS | C62: CW-432 | D62: Sacra, Cyndi | E62: 45809 | J62: Override | K62: By BTRIVETT - 06/02/2025 : dropping off hard copy today. | L62: No | N62: Sacra | O62: =+INDEX('[1]Unit Setup View - Consolidated'!$AS:$AS,MATCH('Rent Insurance S - Consolidated'!$C62,'[1]Unit Setup View - Consolidated'!$AT:$AT,0)) -> 432 Cornwallis Court Ashland VA 23005
A63: =B63&"_"&C63 -> ATS_CW-434 | B63: ATS | C63: CW-434 | D63: Dodge, Geoffrey Longstreth | E63: 45973 | F63: eRenterPlan (LeasingDesk) | G63: 105583642 | H63: 45973 | I63: 46338 | J63: Active | L63: N/A | M63: 100000 | N63: Dodge | O63: =+INDEX('[1]Unit Setup View - Consolidated'!$AS:$AS,MATCH('Rent Insurance S - Consolidated'!$C63,'[1]Unit Setup View - Consolidated'!$AT:$AT,0)) -> 434 Cornwallis Court Ashland VA 23005
A64: =B64&"_"&C64 -> ATS_CW-436 | B64: ATS | C64: CW-436 | D64: White, Karen H | E64: 45797 | F64: eRenterPlan (LeasingDesk) | G64: 103559299 | H64: 45077 | I64: 46173 | J64: Active | L64: N/A | M64: 100000 | N64: White | O64: =+INDEX('[1]Unit Setup View - Consolidated'!$AS:$AS,MATCH('Rent Insurance S - Consolidated'!$C64,'[1]Unit Setup View - Consolidated'!$AT:$AT,0)) -> 436 Cornwallis Court Ashland VA 23005
A65: =B65&"_"&C65 -> ATS_DM-401 | B65: ATS | C65: DM-401 | D65: May, Bonita | E65: 45717 | F65: Praetorian Ins. | G65: PRH5499672 | H65: 45724 | I65: 46089 | J65: Active | L65: Yes | M65: 100000 | N65: May | O65: =+INDEX('[1]Unit Setup View - Consolidated'!$AS:$AS,MATCH('Rent Insurance S - Consolidated'!$C65,'[1]Unit Setup View - Consolidated'!$AT:$AT,0)) -> 401 Drummer Court Ashland VA 23005
A66: =B66&"_"&C66 -> ATS_DM-403 | B66: ATS | C66: DM-403 | D66: Brown, David Antoine | E66: 45809 | F66: eRenterPlan (LeasingDesk) | G66: 104390962 | H66: 45443 | I66: 46173 | J66: Active | L66: N/A | M66: 100000 | N66: Brown | O66: =+INDEX('[1]Unit Setup View - Consolidated'!$AS:$AS,MATCH('Rent Insurance S - Consolidated'!$C66,'[1]Unit Setup View - Consolidated'!$AT:$AT,0)) -> 403 Drummer Court Ashland VA 23005
A67: =B67&"_"&C67 -> ATS_DM-405 | B67: ATS | C67: DM-405 | D67: Brooks, Mark | E67: 45870 | F67: State Farm Insurance | G67: 46EDC3281 | H67: 45859 | I67: 46224 | J67: Active | L67: Yes | M67: 100000 | N67: Brooks | O67: =+INDEX('[1]Unit Setup View - Consolidated'!$AS:$AS,MATCH('Rent Insurance S - Consolidated'!$C67,'[1]Unit Setup View - Consolidated'!$AT:$AT,0)) -> 405 Drummer Court Ashland VA 23005
A68: =B68&"_"&C68 -> ATS_DM-407 | B68: ATS | C68: DM-407 | J68: Vacant | L68: No | O68: =+INDEX('[1]Unit Setup View - Consolidated'!$AS:$AS,MATCH('Rent Insurance S - Consolidated'!$C68,'[1]Unit Setup View - Consolidated'!$AT:$AT,0)) -> 407 Drummer Court Ashland VA 23005
A69: =B69&"_"&C69 -> ATS_DM-409 | B69: ATS | C69: DM-409 | D69: Gibson, Mark | E69: 45778 | J69: Override | K69: By BTRIVETT - 05/01/2024 : Will send insurance | L69: No | N69: Gibson | O69: =+INDEX('[1]Unit Setup View - Consolidated'!$AS:$AS,MATCH('Rent Insurance S - Consolidated'!$C69,'[1]Unit Setup View - Consolidated'!$AT:$AT,0)) -> 409 Drummer Court Ashland VA 23005
A70: =B70&"_"&C70 -> ATS_DM-411 | B70: ATS | C70: DM-411 | D70: Jimenez, Fanny | E70: 45915 | F70: eRenterPlan (LeasingDesk) | G70: 104635453 | H70: 45549 | I70: 45914 | J70: Cancelled | K70: Insured Requested | L70: N/A | M70: 100000 | N70: Jimenez | O70: =+INDEX('[1]Unit Setup View - Consolidated'!$AS:$AS,MATCH('Rent Insurance S - Consolidated'!$C70,'[1]Unit Setup View - Consolidated'!$AT:$AT,0)) -> 411 Drummer Court Ashland VA 23005
A71: =B71&"_"&C71 -> ATS_DM-413 | B71: ATS | C71: DM-413 | D71: Pangelinan, Brianna | E71: 45979 | F71: USAA Insurance Company | G71: CIC-024343041 REN 001 | H71: 45980 | I71: 46345 | J71: Active | L71: Yes | M71: 100000 | N71: Pangelinan | O71: =+INDEX('[1]Unit Setup View - Consolidated'!$AS:$AS,MATCH('Rent Insurance S - Consolidated'!$C71,'[1]Unit Setup View - Consolidated'!$AT:$AT,0)) -> 413 Drummer Court Ashland VA 23005
A72: =B72&"_"&C72 -> ATS_DM-415 | B72: ATS | C72: DM-415 | D72: Pereira Suarez, Romulo Jesus | E72: 45884 | F72: eRenterPlan (LeasingDesk) | G72: 105399479 | H72: 45884 | I72: 46249 | J72: Active | L72: N/A | M72: 100000 | N72: Pereira Suarez | O72: =+INDEX('[1]Unit Setup View - Consolidated'!$AS:$AS,MATCH('Rent Insurance S - Consolidated'!$C72,'[1]Unit Setup View - Consolidated'!$AT:$AT,0)) -> 415 Drummer Court Ashland VA 23005
A73: =B73&"_"&C73 -> ATS_DM-417 | B73: ATS | C73: DM-417 | D73: Sherman, Senese | E73: 45849 | F73: eRenterPlan (LeasingDesk) | G73: 104916741 | H73: 45673 | I73: 46038 | J73: Active | L73: N/A | M73: 100000 | N73: Sherman | O73: =+INDEX('[1]Unit Setup View - Consolidated'!$AS:$AS,MATCH('Rent Insurance S - Consolidated'!$C73,'[1]Unit Setup View - Consolidated'!$AT:$AT,0)) -> 417 Drummer Court Ashland VA 23005
A74: =B74&"_"&C74 -> ATS_DM-419 | B74: ATS | C74: DM-419 | D74: Trivett, Brian Lee | E74: 45323 | F74: Liberty Mutual | G74: H4J-231-915681-40 | H74: 45316 | I74: 45682 | J74: Cancelled | L74: Yes | M74: 100000 | N74: Trivett | O74: =+INDEX('[1]Unit Setup View - Consolidated'!$AS:$AS,MATCH('Rent Insurance S - Consolidated'!$C74,'[1]Unit Setup View - Consolidated'!$AT:$AT,0)) -> 419 Drummer Court Ashland VA 23005
A75: =B75&"_"&C75 -> ATS_GC-300 | B75: ATS | C75: GC-300 | D75: Andrews, Cynthia | E75: 45962 | F75: Grange Insurance | G75: HM5866675 | H75: 45891 | I75: 46256 | J75: Active | L75: Yes | M75: 100000 | N75: Andrews | O75: =+INDEX('[1]Unit Setup View - Consolidated'!$AS:$AS,MATCH('Rent Insurance S - Consolidated'!$C75,'[1]Unit Setup View - Consolidated'!$AT:$AT,0)) -> 300 Glencairn Court Ashland VA 23005
A76: =B76&"_"&C76 -> ATS_GC-301 | B76: ATS | C76: GC-301 | D76: Dean, Lauren | E76: 45943 | F76: eRenterPlan (LeasingDesk) | G76: 103201196 | H76: 44894 | I76: 46355 | J76: Active | L76: N/A | M76: 100000 | N76: Dean | O76: =+INDEX('[1]Unit Setup View - Consolidated'!$AS:$AS,MATCH('Rent Insurance S - Consolidated'!$C76,'[1]Unit Setup View - Consolidated'!$AT:$AT,0)) -> 301 Glencairn Court Ashland VA 23005
A77: =B77&"_"&C77 -> ATS_GC-302 | B77: ATS | C77: GC-302 | J77: Vacant | L77: No | O77: =+INDEX('[1]Unit Setup View - Consolidated'!$AS:$AS,MATCH('Rent Insurance S - Consolidated'!$C77,'[1]Unit Setup View - Consolidated'!$AT:$AT,0)) -> 302 Glencairn Court Ashland VA 23005
A78: =B78&"_"&C78 -> ATS_GC-303 | B78: ATS | C78: GC-303 | J78: Vacant | L78: No | O78: =+INDEX('[1]Unit Setup View - Consolidated'!$AS:$AS,MATCH('Rent Insurance S - Consolidated'!$C78,'[1]Unit Setup View - Consolidated'!$AT:$AT,0)) -> 303 Glencairn Court Ashland VA 23005
A79: =B79&"_"&C79 -> ATS_GC-304 | B79: ATS | C79: GC-304 | D79: Hughes, Michael | E79: 45809 | F79: Travelers Insurance Company | G79: 9867382036341 | H79: 45791 | I79: 46156 | J79: Active | L79: Yes | M79: 100000 | N79: Hughes | O79: =+INDEX('[1]Unit Setup View - Consolidated'!$AS:$AS,MATCH('Rent Insurance S - Consolidated'!$C79,'[1]Unit Setup View - Consolidated'!$AT:$AT,0)) -> 304 Glencairn Court Ashland VA 23005
A80: =B80&"_"&C80 -> ATS_GC-305 | B80: ATS | C80: GC-305 | D80: Freeman, Devonte | E80: 45818 | F80: eRenterPlan (LeasingDesk) | G80: 102693226 | H80: 44658 | I80: 46119 | J80: Active | L80: N/A | M80: 100000 | N80: Freeman | O80: =+INDEX('[1]Unit Setup View - Consolidated'!$AS:$AS,MATCH('Rent Insurance S - Consolidated'!$C80,'[1]Unit Setup View - Consolidated'!$AT:$AT,0)) -> 305 Glencairn Court Ashland VA 23005
A81: =B81&"_"&C81 -> ATS_GC-306 | B81: ATS | C81: GC-306 | D81: Blankenship, Christopher | E81: 45879 | F81: Lemonade | G81: LP26F6B0A06 | H81: 45871 | I81: 46236 | J81: Active | L81: Yes | M81: 100000 | N81: Blankenship | O81: =+INDEX('[1]Unit Setup View - Consolidated'!$AS:$AS,MATCH('Rent Insurance S - Consolidated'!$C81,'[1]Unit Setup View - Consolidated'!$AT:$AT,0)) -> 306 Glencairn Court Ashland VA 23005
A82: =B82&"_"&C82 -> ATS_GC-307 | B82: ATS | C82: GC-307 | D82: Moore, Tamela Patrice | E82: 45611 | F82: eRenterPlan (LeasingDesk) | G82: 105004186 | H82: 45715 | I82: 45806 | J82: Cancelled | K82: Due to Non-payment | L82: N/A | M82: 100000 | N82: Moore | O82: =+INDEX('[1]Unit Setup View - Consolidated'!$AS:$AS,MATCH('Rent Insurance S - Consolidated'!$C82,'[1]Unit Setup View - Consolidated'!$AT:$AT,0)) -> 307 Glencairn Court Ashland VA 23005
A83: =B83&"_"&C83 -> ATS_GC-308 | B83: ATS | C83: GC-308 | D83: Bryant, Karin Ann | E83: 45717 | F83: eRenterPlan (LeasingDesk) | G83: 105543946 | H83: 45952 | I83: 45985 | J83: Pending Cancellation | K83: Due to Non-payment | L83: N/A | M83: 100000 | N83: Bryant | O83: =+INDEX('[1]Unit Setup View - Consolidated'!$AS:$AS,MATCH('Rent Insurance S - Consolidated'!$C83,'[1]Unit Setup View - Consolidated'!$AT:$AT,0)) -> 308 Glencairn Court Ashland VA 23005
A84: =B84&"_"&C84 -> ATS_GC-309 | B84: ATS | C84: GC-309 | D84: Martz, Jeremy | E84: 45759 | F84: trustguard | G84: HM 530042200 | H84: 46020 | I84: 46385 | J84: Future | L84: Yes | M84: 100000 | N84: Martz | O84: =+INDEX('[1]Unit Setup View - Consolidated'!$AS:$AS,MATCH('Rent Insurance S - Consolidated'!$C84,'[1]Unit Setup View - Consolidated'!$AT:$AT,0)) -> 309 Glencairn Court Ashland VA 23005
A85: =B85&"_"&C85 -> ATS_GC-310 | B85: ATS | C85: GC-310 | D85: Marino, Oliver | E85: 45788 | F85: USAA Insurance Company | G85: GAR 017853272 | H85: 45687 | I85: 46052 | J85: Active | L85: Yes | M85: 100000 | N85: Marino | O85: =+INDEX('[1]Unit Setup View - Consolidated'!$AS:$AS,MATCH('Rent Insurance S - Consolidated'!$C85,'[1]Unit Setup View - Consolidated'!$AT:$AT,0)) -> 310 Glencairn Court Ashland VA 23005
A86: =B86&"_"&C86 -> ATS_GC-311 | B86: ATS | C86: GC-311 | D86: Taylor, Jydaisha (JyDaisha) | E86: 45735 | F86: Lemonade | G86: LP8DB9AB8D9 | H86: 45780 | I86: 46145 | J86: Active | L86: Yes | M86: 100000 | N86: Taylor | O86: =+INDEX('[1]Unit Setup View - Consolidated'!$AS:$AS,MATCH('Rent Insurance S - Consolidated'!$C86,'[1]Unit Setup View - Consolidated'!$AT:$AT,0)) -> 311 Glencairn Court Ashland VA 23005
A87: =B87&"_"&C87 -> ATS_GC-312 | B87: ATS | C87: GC-312 | D87: Taylor, Joshua Matthew | E87: 45718 | F87: Assurant Liability | G87: REN4343109 | H87: 45724 | I87: 46089 | J87: Active | L87: Yes | M87: 100000 | N87: Taylor | O87: =+INDEX('[1]Unit Setup View - Consolidated'!$AS:$AS,MATCH('Rent Insurance S - Consolidated'!$C87,'[1]Unit Setup View - Consolidated'!$AT:$AT,0)) -> 312 Glencairn Court Ashland VA 23005
A88: =B88&"_"&C88 -> ATS_GC-313 | B88: ATS | C88: GC-313 | D88: Colson, Sherese | E88: 45868 | F88: Travelers Insurance Company | G88: 6098379696341 | H88: 45868 | I88: 46233 | J88: Active | L88: Yes | M88: 100000 | N88: Colson | O88: =+INDEX('[1]Unit Setup View - Consolidated'!$AS:$AS,MATCH('Rent Insurance S - Consolidated'!$C88,'[1]Unit Setup View - Consolidated'!$AT:$AT,0)) -> 313 Glencairn Court Ashland VA 23005
A89: =B89&"_"&C89 -> ATS_GC-315 | B89: ATS | C89: GC-315 | D89: Smithers, Raymond | E89: 45869 | F89: Farmers Insurance | G89: 935679696 | H89: 45665 | I89: 46030 | J89: Active | L89: Yes | M89: 100000 | N89: Smithers | O89: =+INDEX('[1]Unit Setup View - Consolidated'!$AS:$AS,MATCH('Rent Insurance S - Consolidated'!$C89,'[1]Unit Setup View - Consolidated'!$AT:$AT,0)) -> 315 Glencairn Court Ashland VA 23005
A90: =B90&"_"&C90 -> ATS_GC-317 | B90: ATS | C90: GC-317 | D90: Graziano, Stephanie | E90: 45730 | F90: Liberty Mutual | G90: H4J-231-770423-75 5 5 | H90: 45711 | I90: 46076 | J90: Active | L90: Yes | M90: 100000 | N90: Graziano | O90: =+INDEX('[1]Unit Setup View - Consolidated'!$AS:$AS,MATCH('Rent Insurance S - Consolidated'!$C90,'[1]Unit Setup View - Consolidated'!$AT:$AT,0)) -> 317 Glencairn Court Ashland VA 23005
A91: =B91&"_"&C91 -> ATS_GC-319 | B91: ATS | C91: GC-319 | D91: Warsawski, Volodymyr Vlad | E91: 45784 | J91: Override | K91: By BTRIVETT - 05/08/2025 : waiting on the guarantors to email | L91: No | N91: Warsawski | O91: =+INDEX('[1]Unit Setup View - Consolidated'!$AS:$AS,MATCH('Rent Insurance S - Consolidated'!$C91,'[1]Unit Setup View - Consolidated'!$AT:$AT,0)) -> 319 Glencairn Court Ashland VA 23005
A92: =B92&"_"&C92 -> ATS_GC-321 | B92: ATS | C92: GC-321 | D92: Edwards, Christine | E92: 45839 | F92: Geico | G92: RIN 8823023 | H92: 45821 | I92: 46186 | J92: Active | L92: Yes | M92: 100000 | N92: Edwards | O92: =+INDEX('[1]Unit Setup View - Consolidated'!$AS:$AS,MATCH('Rent Insurance S - Consolidated'!$C92,'[1]Unit Setup View - Consolidated'!$AT:$AT,0)) -> 321 Glencairn Court Ashland VA 23005
A93: =B93&"_"&C93 -> ATS_GC-323 | B93: ATS | C93: GC-323 | D93: Farrington, Maria Ann | E93: 45772 | F93: Geico | G93: REN5441816 | H93: 45773 | I93: 46138 | J93: Active | L93: Yes | M93: 100000 | N93: Farrington | O93: =+INDEX('[1]Unit Setup View - Consolidated'!$AS:$AS,MATCH('Rent Insurance S - Consolidated'!$C93,'[1]Unit Setup View - Consolidated'!$AT:$AT,0)) -> 323 Glencairn Court Ashland VA 23005
A94: =B94&"_"&C94 -> ATS_GC-325 | B94: ATS | C94: GC-325 | D94: Sosa, Jhonathan | E94: 45779 | F94: Progressive Insurance Company | G94: VAA275394 | H94: 45779 | I94: 46144 | J94: Active | L94: Yes | M94: 100000 | N94: Sosa | O94: =+INDEX('[1]Unit Setup View - Consolidated'!$AS:$AS,MATCH('Rent Insurance S - Consolidated'!$C94,'[1]Unit Setup View - Consolidated'!$AT:$AT,0)) -> 325 Glencairn Court Ashland VA 23005
A95: =B95&"_"&C95 -> ATS_GC-327 | B95: ATS | C95: GC-327 | D95: Blanchard, Richard | E95: 45809 | F95: Auto Owners Insurance Co | G95: 5083451101 | H95: 45798 | I95: 46163 | J95: Active | L95: Yes | M95: 300000 | N95: Blanchard | O95: =+INDEX('[1]Unit Setup View - Consolidated'!$AS:$AS,MATCH('Rent Insurance S - Consolidated'!$C95,'[1]Unit Setup View - Consolidated'!$AT:$AT,0)) -> 327 Glencairn Court Ashland VA 23005
A96: =B96&"_"&C96 -> ATS_GC-329 | B96: ATS | C96: GC-329 | D96: Peebles, Oliver | E96: 45957 | J96: None | K96: pdf issue. dropping off hard copy. | L96: No | N96: Peebles | O96: =+INDEX('[1]Unit Setup View - Consolidated'!$AS:$AS,MATCH('Rent Insurance S - Consolidated'!$C96,'[1]Unit Setup View - Consolidated'!$AT:$AT,0)) -> 329 Glencairn Court Ashland VA 23005
A97: =B97&"_"&C97 -> ATS_GC-331 | B97: ATS | C97: GC-331 | D97: Walker, Myranda | E97: 45627 | F97: Progressive Insurance Company | G97: VAA115151 | H97: 45627 | I97: 45992 | J97: Pending Cancellation | L97: Yes | M97: 100000 | N97: Walker | O97: =+INDEX('[1]Unit Setup View - Consolidated'!$AS:$AS,MATCH('Rent Insurance S - Consolidated'!$C97,'[1]Unit Setup View - Consolidated'!$AT:$AT,0)) -> 331 Glencairn Court Ashland VA 23005
A98: =B98&"_"&C98 -> ATS_GC-333 | B98: ATS | C98: GC-333 | D98: Spikes, Bridget | E98: 45841 | F98: Lemonade | G98: LP46C703584 | H98: 45841 | I98: 46206 | J98: Active | L98: Yes | M98: 100000 | N98: Spikes | O98: =+INDEX('[1]Unit Setup View - Consolidated'!$AS:$AS,MATCH('Rent Insurance S - Consolidated'!$C98,'[1]Unit Setup View - Consolidated'!$AT:$AT,0)) -> 333 Glencairn Court Ashland VA 23005
A99: =B99&"_"&C99 -> ATS_GC-335 | B99: ATS | C99: GC-335 | D99: West, Hadonish | E99: 45677 | F99: Homesite Insurance | G99: 38723486 | H99: 45678 | I99: 46043 | J99: Active | L99: Yes | M99: 100000 | N99: West | O99: =+INDEX('[1]Unit Setup View - Consolidated'!$AS:$AS,MATCH('Rent Insurance S - Consolidated'!$C99,'[1]Unit Setup View - Consolidated'!$AT:$AT,0)) -> 335 Glencairn Court Ashland VA 23005
A100: =B100&"_"&C100 -> ATS_HG-200 | B100: ATS | C100: HG-200 | D100: Clavijo, Carmenza | E100: 45737 | F100: eRenterPlan (LeasingDesk) | G100: 105055245 | H100: 45738 | I100: 46103 | J100: Active | L100: N/A | M100: 100000 | N100: Clavijo | O100: =+INDEX('[1]Unit Setup View - Consolidated'!$AS:$AS,MATCH('Rent Insurance S - Consolidated'!$C100,'[1]Unit Setup View - Consolidated'!$AT:$AT,0)) -> 200 Holly Green Court Ashland VA 23005
...
